MANIFEST.in
setup.py
docs/HISTORY.txt
docs/INSTALL.txt
docs/LICENSE.GPL
docs/LICENSE.txt
quintagroup/__init__.py
quintagroup.sunrain.policy.egg-info/PKG-INFO
quintagroup.sunrain.policy.egg-info/SOURCES.txt
quintagroup.sunrain.policy.egg-info/dependency_links.txt
quintagroup.sunrain.policy.egg-info/entry_points.txt
quintagroup.sunrain.policy.egg-info/namespace_packages.txt
quintagroup.sunrain.policy.egg-info/not-zip-safe
quintagroup.sunrain.policy.egg-info/requires.txt
quintagroup.sunrain.policy.egg-info/top_level.txt
quintagroup/sunrain/__init__.py
quintagroup/sunrain/policy/README.txt
quintagroup/sunrain/policy/__init__.py
quintagroup/sunrain/policy/configure.zcml
quintagroup/sunrain/policy/profiles/default/actions.xml
quintagroup/sunrain/policy/profiles/default/metadata.xml