Metadata-Version: 1.0
Name: quintagroup.sunrain.policy
Version: 1.0
Summary: UNKNOWN
Home-page: http://skins.quintagroup.com/sunrain
Author: Quintagroup
Author-email: skins@quintagroup.com
License: GPL
Keywords: web zope plone theme diazo quintagroup
Platform: UNKNOWN
Classifier: Framework :: Plone
Classifier: Intended Audience :: Developers
Classifier: Topic :: Software Development :: Libraries :: Python Modules
Classifier: License :: OSI Approved :: GNU General Public License (GPL)
